LICENSE
mdx_alerts.py
mdx_alerts-1.0.1.dist-info/entry_points.txt
mdx_alerts-1.0.1.dist-info/LICENSE
mdx_alerts-1.0.1.dist-info/WHEEL
mdx_alerts-1.0.1.dist-info/METADATA
mdx_alerts-1.0.1.dist-info/RECORD
