Metadata-Version: 2.1
Name: mdx-alerts
Version: 1.0.1
Summary: Python-Markdown extension to support bootstrap alerts
Home-page: https://github.com/DahlitzFlorian/python-markdown-bootstrap-alerts
License: MIT
Keywords: python-markdown,extension,python-markdown extension,bootstrap alerts,bootstrap alerts extension
Author: Florian Dahlitz
Author-email: f2dahlitz@freenet.de
Requires-Python: >=3.6,<4.0
Classifier: License :: OSI Approved :: MIT License
Classifier: Programming Language :: Python :: 3
Classifier: Programming Language :: Python :: 3.6
Classifier: Programming Language :: Python :: 3.7
Classifier: Programming Language :: Python :: 3.8
Classifier: Programming Language :: Python :: 3.9
Requires-Dist: Markdown (>=3.3.4,<4.0.0)
Project-URL: Repository, https://github.com/DahlitzFlorian/python-markdown-bootstrap-alerts
